Week 5/opcode_decoder.v
//====================================================
// decoder.v
//====================================================

//----------------------------------------------------
// 1-to-2 Decoder
//----------------------------------------------------
module decoder_1to2 (
    input  wire En,
    input  wire w0,
    output wire y0,
    output wire y1
);

assign y0 = En & (~w0);
assign y1 = En & ( w0);

endmodule


//----------------------------------------------------
// 2-to-4 Decoder
//----------------------------------------------------
module decoder_2to4 (
    input  wire En,
    input  wire w0,
    input  wire w1,

    output wire y0,
    output wire y1,
    output wire y2,
    output wire y3
);

assign y0 = En & (~w1) & (~w0);
assign y1 = En & (~w1) & ( w0);
assign y2 = En & ( w1) & (~w0);
assign y3 = En & ( w1) & ( w0);

endmodule


//----------------------------------------------------
// 4-to-16 Decoder
//----------------------------------------------------
module decoder_4to16 (
    input  wire En,
    input  wire w0,
    input  wire w1,
    input  wire w2,
    input  wire w3,

    output wire y0,
    output wire y1,
    output wire y2,
    output wire y3,
    output wire y4,
    output wire y5,
    output wire y6,
    output wire y7,
    output wire y8,
    output wire y9,
    output wire y10,
    output wire y11,
    output wire y12,
    output wire y13,
    output wire y14,
    output wire y15
);

wire en0;
wire en1;
wire en2;
wire en3;

// Decode upper two bits (w3,w2)
decoder_2to4 upper_decoder (
    .En(En),
    .w0(w2),
    .w1(w3),

    .y0(en0),
    .y1(en1),
    .y2(en2),
    .y3(en3)
);

// Decode lower two bits (w1,w0)

decoder_2to4 lower_decoder0 (
    .En(en0),
    .w0(w0),
    .w1(w1),

    .y0(y0),
    .y1(y1),
    .y2(y2),
    .y3(y3)
);

decoder_2to4 lower_decoder1 (
    .En(en1),
    .w0(w0),
    .w1(w1),

    .y0(y4),
    .y1(y5),
    .y2(y6),
    .y3(y7)
);

decoder_2to4 lower_decoder2 (
    .En(en2),
    .w0(w0),
    .w1(w1),

    .y0(y8),
    .y1(y9),
    .y2(y10),
    .y3(y11)
);

decoder_2to4 lower_decoder3 (
    .En(en3),
    .w0(w0),
    .w1(w1),

    .y0(y12),
    .y1(y13),
    .y2(y14),
    .y3(y15)
);

endmodule

//----------------------------------------------------
// Opcode Decoder
//----------------------------------------------------
module opcode_decoder(
    input  wire [15:0] instruction,

    // Main opcode outputs
    output wire NOOP,
    output wire MOVE,
    output wire LOADI_LOADP,
    output wire ADD,
    output wire ADDI,
    output wire SUB,
    output wire SUBI,
    output wire LOAD,
    output wire LOADF,
    output wire STORE,
    output wire STOREF,
    output wire CMP,
    output wire JUMP,

    // MOVE sub-opcodes
    output wire INPUTC,
    output wire INPUTCF,
    output wire INPUTD,
    output wire INPUTDF,

    // SHIFT sub-opcodes
    output wire SHIFTL,
    output wire SHIFTR,

    // BRANCH sub-opcodes
    output wire BRE_BRZ,
    output wire BRNE_BRNZ,
    output wire BRG,
    output wire BRGE
);

    // Unused outputs from the main decoder
    wire y1_unused;
    wire y12_enable;
    wire y15_enable;

    //------------------------------------------------
    // Main 4-to-16 Opcode Decoder
    //------------------------------------------------
    decoder_4to16 main_decoder (
        .En(1'b1),

        .w0(instruction[12]),
        .w1(instruction[13]),
        .w2(instruction[14]),
        .w3(instruction[15]),

        .y0(NOOP),
        .y1(y1_unused),
        .y2(MOVE),
        .y3(LOADI_LOADP),
        .y4(ADD),
        .y5(ADDI),
        .y6(SUB),
        .y7(SUBI),
        .y8(LOAD),
        .y9(LOADF),
        .y10(STORE),
        .y11(STOREF),
        .y12(y12_enable),
        .y13(CMP),
        .y14(JUMP),
        .y15(y15_enable)
    );

    //------------------------------------------------
    // MOVE Sub Decoder
    // Enabled when opcode = MOVE
    // Uses instruction[9:8]
    //------------------------------------------------
    decoder_2to4 move_decoder (
        .En(y1_unused),

        .w0(instruction[8]),
        .w1(instruction[9]),

        .y0(INPUTC),
        .y1(INPUTCF),
        .y2(INPUTD),
        .y3(INPUTDF)
    );

    //------------------------------------------------
    // SHIFT Decoder
    // Enabled by y12
    // Uses instruction[8]
    //------------------------------------------------
    decoder_1to2 shift_decoder (
        .En(y12_enable),

        .w0(instruction[8]),

        .y0(SHIFTL),
        .y1(SHIFTR)
    );

    //------------------------------------------------
    // Branch Decoder
    // Enabled by y15
    // Uses instruction[9:8]
    //------------------------------------------------
    decoder_2to4 branch_decoder (
        .En(y15_enable),

        .w0(instruction[8]),
        .w1(instruction[9]),

        .y0(BRE_BRZ),
        .y1(BRNE_BRNZ),
        .y2(BRG),
        .y3(BRGE)
    );

endmodule

// instruction[15:12]
//         │
//         ▼
//    decoder_4to16
//         │
//         ├── y0  → NOOP
//         ├── y1  ─────────► decoder_2to4 → INPUTC, INPUTCF, INPUTD, INPUTDF
//         ├── y2  → MOVE 
//         ├── y3  → LOADI_LOADP
//         ├── y4  → ADD
//         ├── y5  → ADDI
//         ├── y6  → SUB
//         ├── y7  → SUBI
//         ├── y8  → LOAD
//         ├── y9  → LOADF
//         ├── y10 → STORE
//         ├── y11 → STOREF
//         ├── y12 ────────────────► decoder_1to2 → SHIFTL, SHIFTR
//         ├── y13 → CMP
//         ├── y14 → JUMP
//         └── y15 ────────────────► decoder_2to4 → BRE_BRZ, BRNE_BRNZ, BRG, BRGE

Week 4/decoder_tb.v
`timescale 1ns/1ps

`define RED    "\033[31m"
`define GREEN  "\033[32m"
`define RESET  "\033[0m"

module decoder_tb;

reg [15:0] instruction;

// Main opcode outputs
wire NOOP;
wire MOVE;
wire LOADI_LOADP;
wire ADD;
wire ADDI;
wire SUB;
wire SUBI;
wire LOAD;
wire LOADF;
wire STORE;
wire STOREF;
wire CMP;
wire JUMP;

// MOVE sub-opcodes
wire INPUTC;
wire INPUTCF;
wire INPUTD;
wire INPUTDF;

// SHIFT sub-opcodes
wire SHIFTL;
wire SHIFTR;

// BRANCH sub-opcodes
wire BRE_BRZ;
wire BRNE_BRNZ;
wire BRG;
wire BRGE;


//----------------------------------------------
// Instantiate DUT
//----------------------------------------------
opcode_decoder DUT (

    .instruction(instruction),

    .NOOP(NOOP),
    .MOVE(MOVE),
    .LOADI_LOADP(LOADI_LOADP),
    .ADD(ADD),
    .ADDI(ADDI),
    .SUB(SUB),
    .SUBI(SUBI),
    .LOAD(LOAD),
    .LOADF(LOADF),
    .STORE(STORE),
    .STOREF(STOREF),
    .CMP(CMP),
    .JUMP(JUMP),

    .INPUTC(INPUTC),
    .INPUTCF(INPUTCF),
    .INPUTD(INPUTD),
    .INPUTDF(INPUTDF),

    .SHIFTL(SHIFTL),
    .SHIFTR(SHIFTR),

    .BRE_BRZ(BRE_BRZ),
    .BRNE_BRNZ(BRNE_BRNZ),
    .BRG(BRG),
    .BRGE(BRGE)

);


//----------------------------------------------
// Test Task
//----------------------------------------------
task check;

input expected;
input actual;
input [127:0] name;

begin

if (actual === expected)
    $display("%s : %sPASS%s", name, `GREEN, `RESET);
else
    $display("%s : %sFAIL%s", name, `RED, `RESET);

end

endtask


initial begin
    $dumpfile("decoder.vcd");
    $dumpvars(0, decoder_tb);
end

//----------------------------------------------
// Test Sequence
//----------------------------------------------
initial begin

//------------------------------------------------
// Main Opcodes
//------------------------------------------------

instruction = 16'b0000_0000_00000000;
#10;
check(1,NOOP,"NOOP");

instruction = 16'b0010_0000_00000000;
#10;
check(1,MOVE,"MOVE");

instruction = 16'b0011_0000_00000000;
#10;
check(1,LOADI_LOADP,"LOADI_LOADP");

instruction = 16'b0100_0000_00000000;
#10;
check(1,ADD,"ADD");

instruction = 16'b0101_0000_00000000;
#10;
check(1,ADDI,"ADDI");

instruction = 16'b0110_0000_00000000;
#10;
check(1,SUB,"SUB");

instruction = 16'b0111_0000_00000000;
#10;
check(1,SUBI,"SUBI");

instruction = 16'b1000_0000_00000000;
#10;
check(1,LOAD,"LOAD");

instruction = 16'b1001_0000_00000000;
#10;
check(1,LOADF,"LOADF");

instruction = 16'b1010_0000_00000000;
#10;
check(1,STORE,"STORE");

instruction = 16'b1011_0000_00000000;
#10;
check(1,STOREF,"STOREF");

instruction = 16'b1101_0000_00000000;
#10;
check(1,CMP,"CMP");

instruction = 16'b1110_0000_00000000;
#10;
check(1,JUMP,"JUMP");


//------------------------------------------------
// MOVE Sub Decoder
//------------------------------------------------

instruction = 16'b0001_0000_00000000;
#10;
check(1,INPUTC,"INPUTC");

instruction = 16'b0001_0001_00000000;
#10;
check(1,INPUTCF,"INPUTCF");

instruction = 16'b0001_0010_00000000;
#10;
check(1,INPUTD,"INPUTD");

instruction = 16'b0001_0011_00000000;
#10;
check(1,INPUTDF,"INPUTDF");


//------------------------------------------------
// SHIFT Decoder
//------------------------------------------------

instruction = 16'b1100_0000_00000000;
#10;
check(1,SHIFTL,"SHIFTL");

instruction = 16'b1100_0001_00000000;
#10;
check(1,SHIFTR,"SHIFTR");


//------------------------------------------------
// Branch Decoder
//------------------------------------------------

instruction = 16'b1111_0000_00000000;
#10;
check(1,BRE_BRZ,"BRE_BRZ");

instruction = 16'b1111_0001_00000000;
#10;
check(1,BRNE_BRNZ,"BRNE_BRNZ");

instruction = 16'b1111_0010_00000000;
#10;
check(1,BRG,"BRG");

instruction = 16'b1111_0011_00000000;
#10;
check(1,BRGE,"BRGE");


$display("");
$display("==================================");
$display(" ALL TESTS COMPLETED ");
$display("==================================");

$finish;

end

endmodule

Week 4/decoder.vcd
$date
	Wed Jul 15 11:37:59 2026
$end
$version
	Icarus Verilog
$end
$timescale
	1ps
$end
$scope module decoder_tb $end
$var wire 1 ! SUBI $end
$var wire 1 " SUB $end
$var wire 1 # STOREF $end
$var wire 1 $ STORE $end
$var wire 1 % SHIFTR $end
$var wire 1 & SHIFTL $end
$var wire 1 ' NOOP $end
$var wire 1 ( MOVE $end
$var wire 1 ) LOADI_LOADP $end
$var wire 1 * LOADF $end
$var wire 1 + LOAD $end
$var wire 1 , JUMP $end
$var wire 1 - INPUTDF $end
$var wire 1 . INPUTD $end
$var wire 1 / INPUTCF $end
$var wire 1 0 INPUTC $end
$var wire 1 1 CMP $end
$var wire 1 2 BRNE_BRNZ $end
$var wire 1 3 BRGE $end
$var wire 1 4 BRG $end
$var wire 1 5 BRE_BRZ $end
$var wire 1 6 ADDI $end
$var wire 1 7 ADD $end
$var reg 16 8 instruction [15:0] $end
$scope module DUT $end
$var wire 16 9 instruction [15:0] $end
$var wire 1 : y1_unused $end
$var wire 1 ; y15_enable $end
$var wire 1 < y12_enable $end
$var wire 1 ! SUBI $end
$var wire 1 " SUB $end
$var wire 1 # STOREF $end
$var wire 1 $ STORE $end
$var wire 1 % SHIFTR $end
$var wire 1 & SHIFTL $end
$var wire 1 ' NOOP $end
$var wire 1 ( MOVE $end
$var wire 1 ) LOADI_LOADP $end
$var wire 1 * LOADF $end
$var wire 1 + LOAD $end
$var wire 1 , JUMP $end
$var wire 1 - INPUTDF $end
$var wire 1 . INPUTD $end
$var wire 1 / INPUTCF $end
$var wire 1 0 INPUTC $end
$var wire 1 1 CMP $end
$var wire 1 2 BRNE_BRNZ $end
$var wire 1 3 BRGE $end
$var wire 1 4 BRG $end
$var wire 1 5 BRE_BRZ $end
$var wire 1 6 ADDI $end
$var wire 1 7 ADD $end
$scope module branch_decoder $end
$var wire 1 = w0 $end
$var wire 1 > w1 $end
$var wire 1 5 y0 $end
$var wire 1 2 y1 $end
$var wire 1 4 y2 $end
$var wire 1 3 y3 $end
$var wire 1 ; En $end
$upscope $end
$scope module main_decoder $end
$var wire 1 ? En $end
$var wire 1 @ w0 $end
$var wire 1 A w1 $end
$var wire 1 B w2 $end
$var wire 1 C w3 $end
$var wire 1 * y9 $end
$var wire 1 + y8 $end
$var wire 1 ! y7 $end
$var wire 1 " y6 $end
$var wire 1 6 y5 $end
$var wire 1 7 y4 $end
$var wire 1 ) y3 $end
$var wire 1 ( y2 $end
$var wire 1 ; y15 $end
$var wire 1 , y14 $end
$var wire 1 1 y13 $end
$var wire 1 < y12 $end
$var wire 1 # y11 $end
$var wire 1 $ y10 $end
$var wire 1 : y1 $end
$var wire 1 ' y0 $end
$var wire 1 D en3 $end
$var wire 1 E en2 $end
$var wire 1 F en1 $end
$var wire 1 G en0 $end
$scope module lower_decoder0 $end
$var wire 1 @ w0 $end
$var wire 1 A w1 $end
$var wire 1 ' y0 $end
$var wire 1 : y1 $end
$var wire 1 ( y2 $end
$var wire 1 ) y3 $end
$var wire 1 G En $end
$upscope $end
$scope module lower_decoder1 $end
$var wire 1 @ w0 $end
$var wire 1 A w1 $end
$var wire 1 7 y0 $end
$var wire 1 6 y1 $end
$var wire 1 " y2 $end
$var wire 1 ! y3 $end
$var wire 1 F En $end
$upscope $end
$scope module lower_decoder2 $end
$var wire 1 @ w0 $end
$var wire 1 A w1 $end
$var wire 1 + y0 $end
$var wire 1 * y1 $end
$var wire 1 $ y2 $end
$var wire 1 # y3 $end
$var wire 1 E En $end
$upscope $end
$scope module lower_decoder3 $end
$var wire 1 @ w0 $end
$var wire 1 A w1 $end
$var wire 1 < y0 $end
$var wire 1 1 y1 $end
$var wire 1 , y2 $end
$var wire 1 ; y3 $end
$var wire 1 D En $end
$upscope $end
$scope module upper_decoder $end
$var wire 1 ? En $end
$var wire 1 B w0 $end
$var wire 1 C w1 $end
$var wire 1 G y0 $end
$var wire 1 F y1 $end
$var wire 1 E y2 $end
$var wire 1 D y3 $end
$upscope $end
$upscope $end
$scope module move_decoder $end
$var wire 1 : En $end
$var wire 1 H w0 $end
$var wire 1 I w1 $end
$var wire 1 0 y0 $end
$var wire 1 / y1 $end
$var wire 1 . y2 $end
$var wire 1 - y3 $end
$upscope $end
$scope module shift_decoder $end
$var wire 1 < En $end
$var wire 1 J w0 $end
$var wire 1 & y0 $end
$var wire 1 % y1 $end
$upscope $end
$upscope $end
$scope task check $end
$var reg 1 K actual $end
$var reg 1 L expected $end
$var reg 128 M name [127:0] $end
$upscope $end
$upscope $end
$enddefinitions $end
$comment Show the parameter values. $end
$dumpall
$end
#0
$dumpvars
bx M
xL
xK
0J
0I
0H
1G
0F
0E
0D
0C
0B
0A
0@
1?
0>
0=
0<
0;
0:
b0 9
b0 8
07
06
05
04
03
02
01
00
0/
0.
0-
0,
0+
0*
0)
0(
1'
0&
0%
0$
0#
0"
0!
$end
#10000
0'
1(
1A
b10000000000000 8
b10000000000000 9
b1001110010011110100111101010000 M
1K
1L
#20000
0(
1)
1@
b11000000000000 8
b11000000000000 9
b1001101010011110101011001000101 M
#30000
17
0G
0)
1F
0@
0A
1B
b100000000000000 8
b100000000000000 9
b100110001001111010000010100010001001001010111110100110001001111010000010100010001010000 M
#40000
07
16
1@
b101000000000000 8
b101000000000000 9
b10000010100010001000100 M
#50000
1"
06
0@
1A
b110000000000000 8
b110000000000000 9
b1000001010001000100010001001001 M
#60000
0"
1!
1@
b111000000000000 8
b111000000000000 9
b10100110101010101000010 M
#70000
1+
1E
0!
0F
0@
0A
0B
1C
b1000000000000000 8
b1000000000000000 9
b1010011010101010100001001001001 M
#80000
0+
1*
1@
b1001000000000000 8
b1001000000000000 9
b1001100010011110100000101000100 M
#90000
1$
0*
0@
1A
b1010000000000000 8
b1010000000000000 9
b100110001001111010000010100010001000110 M
#100000
0$
1#
1@
b1011000000000000 8
b1011000000000000 9
b101001101010100010011110101001001000101 M
#110000
11
0#
0E
1D
0A
1B
b1101000000000000 8
b1101000000000000 9
b10100110101010001001111010100100100010101000110 M
#120000
1,
01
0@
1A
b1110000000000000 8
b1110000000000000 9
b10000110100110101010000 M
#130000
10
1:
0,
1G
0D
1@
0A
0B
0C
b1000000000000 8
b1000000000000 9
b1001010010101010100110101010000 M
#140000
00
1/
1H
1J
1=
b1000100000000 8
b1000100000000 9
b10010010100111001010000010101010101010001000011 M
#150000
1.
0/
0H
1I
0J
0=
1>
b1001000000000 8
b1001000000000 9
b1001001010011100101000001010101010101000100001101000110 M
#160000
0.
1-
1H
1J
1=
b1001100000000 8
b1001100000000 9
b10010010100111001010000010101010101010001000100 M
#170000
1&
0'
07
1<
0G
0:
0F
1D
0-
0@
1B
1C
0H
0I
0J
0=
0>
b1100000000000000 8
b1100000000000000 9
b1001001010011100101000001010101010101000100010001000110 M
#180000
0&
1%
1H
1J
1=
b1100000100000000 8
b1100000100000000 9
b10100110100100001001001010001100101010001001100 M
#190000
15
0<
0&
01
1;
0%
1@
1A
0H
0J
0=
b1111000000000000 8
b1111000000000000 9
b10100110100100001001001010001100101010001010010 M
#200000
05
12
1H
1J
1=
b1111000100000000 8
b1111000100000000 9
b1000010010100100100010101011111010000100101001001011010 M
#210000
14
02
0H
1I
0J
0=
1>
b1111001000000000 8
b1111001000000000 9
b10000100101001001001110010001010101111101000010010100100100111001011010 M
#220000
04
13
1H
1J
1=
b1111001100000000 8
b1111001100000000 9
b10000100101001001000111 M
#230000
b1000010010100100100011101000101 M
