Week 5/alu.v
//====================================================
// alu.v
// i281 CPU Arithmetic Logic Unit
//====================================================

module alu(

    input  wire [7:0] A,
    input  wire [7:0] B,
    input  wire [2:0] alu_op,

    output reg  [7:0] result,

    output reg  zero,
    output reg  carry,
    output reg  negative

);

    // Internal 9-bit register to detect carry
    reg [8:0] temp;

    always @(*) begin

        // Default values
        result   = 8'd0;
        temp     = 9'd0;

        zero     = 1'b0;
        carry    = 1'b0;
        negative = 1'b0;

        case(alu_op)

            //------------------------------------------------
            // ADD
            //------------------------------------------------
            3'b000: begin

                temp   = A + B;
                result = temp[7:0];
                carry  = temp[8];

            end

            //------------------------------------------------
            // SUB
            //------------------------------------------------
            3'b001: begin

                temp   = {1'b0,A} - {1'b0,B};
                result = temp[7:0];
                carry  = temp[8];

            end

            //------------------------------------------------
            // CMP (same as SUB, only flags matter later)
            //------------------------------------------------
            3'b010: begin

                temp   = {1'b0,A} - {1'b0,B};
                result = temp[7:0];
                carry  = temp[8];

            end

            //------------------------------------------------
            // SHIFT LEFT
            //------------------------------------------------
            3'b011: begin

                result = A << 1;
                carry  = A[7];

            end

            //------------------------------------------------
            // SHIFT RIGHT
            //------------------------------------------------
            3'b100: begin

                result = A >> 1;
                carry  = A[0];

            end

            //------------------------------------------------
            // PASS A
            //------------------------------------------------
            3'b101: begin

                result = A;

            end

            //------------------------------------------------
            // PASS B
            //------------------------------------------------
            3'b110: begin

                result = B;

            end

            //------------------------------------------------
            // Reserved
            //------------------------------------------------
            default: begin

                result = 8'd0;

            end

        endcase

        //------------------------------------------------
        // Common Flag Generation
        //------------------------------------------------

        zero = (result == 8'd0);

        negative = result[7];

    end

endmodule

Week 5/tb_alu.v
`timescale 1ns/1ps

module tb_alu;

    //---------------------------------------
    // Inputs
    //---------------------------------------

    reg [7:0] A;
    reg [7:0] B;
    reg [2:0] alu_op;

    //---------------------------------------
    // Outputs
    //---------------------------------------

    wire [7:0] result;
    wire zero;
    wire carry;
    wire negative;

    //---------------------------------------
    // Statistics
    //---------------------------------------

    integer passed;
    integer failed;

    //---------------------------------------
    // Instantiate ALU
    //---------------------------------------

    alu uut(

        .A(A),
        .B(B),
        .alu_op(alu_op),

        .result(result),

        .zero(zero),
        .carry(carry),
        .negative(negative)

    );

    //---------------------------------------
    // Test Procedure
    //---------------------------------------

    initial begin

        $dumpfile("alu.vcd");
        $dumpvars(0, tb_alu);

        passed = 0;
        failed = 0;

        $display("");
        $display("======================================");
        $display("        ALU TESTBENCH START");
        $display("======================================");

        //-----------------------------------
        // TEST 1 : ADD
        //-----------------------------------

        A = 8'd20;
        B = 8'd10;
        alu_op = 3'b000;

        #5;

        if(result == 30 && carry == 0 && zero == 0)
        begin
            $display("PASS : ADD");
            passed = passed + 1;
        end
        else
        begin
            $display("FAIL : ADD");
            $display("Expected Result = 30");
            $display("Obtained Result = %0d", result);
            failed = failed + 1;
        end

        //-----------------------------------
        // TEST 2 : ADD with Carry
        //-----------------------------------

        A = 8'd255;
        B = 8'd1;
        alu_op = 3'b000;

        #5;

        if(result == 0 && carry == 1 && zero == 1)
        begin
            $display("PASS : ADD Carry");
            passed = passed + 1;
        end
        else
        begin
            $display("FAIL : ADD Carry");
            failed = failed + 1;
        end

        //-----------------------------------
        // TEST 3 : SUB
        //-----------------------------------

        A = 8'd50;
        B = 8'd20;
        alu_op = 3'b001;

        #5;

        if(result == 30)
        begin
            $display("PASS : SUB");
            passed = passed + 1;
        end
        else
        begin
            $display("FAIL : SUB");
            failed = failed + 1;
        end

        //-----------------------------------
        // TEST 4 : CMP
        //-----------------------------------

        A = 8'd25;
        B = 8'd25;
        alu_op = 3'b010;

        #5;

        if(zero == 1)
        begin
            $display("PASS : CMP Equal");
            passed = passed + 1;
        end
        else
        begin
            $display("FAIL : CMP Equal");
            failed = failed + 1;
        end

        //-----------------------------------
        // TEST 5 : SHIFT LEFT
        //-----------------------------------

        A = 8'b00001111;
        B = 0;
        alu_op = 3'b011;

        #5;

        if(result == 8'b00011110)
        begin
            $display("PASS : SHIFT LEFT");
            passed = passed + 1;
        end
        else
        begin
            $display("FAIL : SHIFT LEFT");
            failed = failed + 1;
        end

        //-----------------------------------
        // TEST 6 : SHIFT RIGHT
        //-----------------------------------

        A = 8'b00001110;
        B = 0;
        alu_op = 3'b100;

        #5;

        if(result == 8'b00000111)
        begin
            $display("PASS : SHIFT RIGHT");
            passed = passed + 1;
        end
        else
        begin
            $display("FAIL : SHIFT RIGHT");
            failed = failed + 1;
        end

        //-----------------------------------
        // TEST 7 : PASS A
        //-----------------------------------

        A = 8'd99;
        B = 8'd15;
        alu_op = 3'b101;

        #5;

        if(result == 99)
        begin
            $display("PASS : PASS A");
            passed = passed + 1;
        end
        else
        begin
            $display("FAIL : PASS A");
            failed = failed + 1;
        end

        //-----------------------------------
        // TEST 8 : PASS B
        //-----------------------------------

        A = 8'd12;
        B = 8'd44;
        alu_op = 3'b110;

        #5;

        if(result == 44)
        begin
            $display("PASS : PASS B");
            passed = passed + 1;
        end
        else
        begin
            $display("FAIL : PASS B");
            failed = failed + 1;
        end

        //-----------------------------------
        // SUMMARY
        //-----------------------------------

        $display("");
        $display("======================================");
        $display("Tests Passed : %0d", passed);
        $display("Tests Failed : %0d", failed);
        $display("======================================");

        if(failed == 0)
            $display("ALL TESTS PASSED");
        else
            $display("SOME TESTS FAILED");

        $display("======================================");

        #10;

        $finish;

    end

endmodule

Week 5/alu.vcd
$date
	Wed Jul 15 17:02:35 2026
$end
$version
	Icarus Verilog
$end
$timescale
	1ps
$end
$scope module tb_alu $end
$var wire 1 ! zero $end
$var wire 8 " result [7:0] $end
$var wire 1 # negative $end
$var wire 1 $ carry $end
$var reg 8 % A [7:0] $end
$var reg 8 & B [7:0] $end
$var reg 3 ' alu_op [2:0] $end
$var integer 32 ( failed [31:0] $end
$var integer 32 ) passed [31:0] $end
$scope module uut $end
$var wire 8 * A [7:0] $end
$var wire 8 + B [7:0] $end
$var wire 3 , alu_op [2:0] $end
$var reg 1 $ carry $end
$var reg 1 # negative $end
$var reg 8 - result [7:0] $end
$var reg 9 . temp [8:0] $end
$var reg 1 ! zero $end
$upscope $end
$upscope $end
$enddefinitions $end
$comment Show the parameter values. $end
$dumpall
$end
#0
$dumpvars
b11110 .
b11110 -
b0 ,
b1010 +
b10100 *
b0 )
b0 (
b0 '
b1010 &
b10100 %
0$
0#
b11110 "
0!
$end
#5000
1!
1$
b100000000 .
b0 "
b0 -
b1 &
b1 +
b11111111 %
b11111111 *
b1 )
#10000
b11110 "
b11110 -
0$
0!
b11110 .
b1 '
b1 ,
b10100 &
b10100 +
b110010 %
b110010 *
b10 )
#15000
1!
b0 .
b0 "
b0 -
b10 '
b10 ,
b11001 &
b11001 +
b11001 %
b11001 *
b11 )
#20000
b11110 "
b11110 -
0!
b11 '
b11 ,
b0 &
b0 +
b1111 %
b1111 *
b100 )
#25000
b111 "
b111 -
b100 '
b100 ,
b1110 %
b1110 *
b101 )
#30000
b1100011 "
b1100011 -
b101 '
b101 ,
b1111 &
b1111 +
b1100011 %
b1100011 *
b110 )
#35000
b101100 "
b101100 -
b110 '
b110 ,
b101100 &
b101100 +
b1100 %
b1100 *
b111 )
#40000
b1000 )
