Week 6/register_file.v
//====================================================
// register_file.v
// i281 CPU Register File
//====================================================

module register_file(

    input wire clk,
    input wire reset,

    // Register Write Enable
    input wire reg_write,

    // Destination Register Select
    input wire [1:0] write_sel,

    // Source Register 1 Select
    input wire [1:0] read_sel1,

    // Source Register 2 Select
    input wire [1:0] read_sel2,

    // Data to be written
    input wire [7:0] write_data,

    // Outputs
    output wire [7:0] read_data1,
    output wire [7:0] read_data2,

    // Debug Outputs
    output wire [7:0] regA,
    output wire [7:0] regB,
    output wire [7:0] regC,
    output wire [7:0] regD

);
    //------------------------------------------------
    // Registers
    //------------------------------------------------
    reg [7:0] A;
    reg [7:0] B;
    reg [7:0] C;
    reg [7:0] D;
    //------------------------------------------------
    // Reset + Write
    //------------------------------------------------
    always @(posedge clk or posedge reset)
    begin
        if(reset)
        begin
            A <= 8'd0;
            B <= 8'd0;
            C <= 8'd0;
            D <= 8'd0;
        end
        else if(reg_write)
        begin
            case(write_sel)

                2'b00:
                    A <= write_data;

                2'b01:
                    B <= write_data;

                2'b10:
                    C <= write_data;

                2'b11:
                    D <= write_data;
            endcase
        end
    end
    //------------------------------------------------
    // Read Port 1
    //------------------------------------------------
    assign read_data1 =
            (read_sel1 == 2'b00) ? A :
            (read_sel1 == 2'b01) ? B :
            (read_sel1 == 2'b10) ? C :
                                  D;
    //------------------------------------------------
    // Read Port 2
    //------------------------------------------------
    assign read_data2 =
            (read_sel2 == 2'b00) ? A :
            (read_sel2 == 2'b01) ? B :
            (read_sel2 == 2'b10) ? C :
                                  D;
    //------------------------------------------------
    // Debug Outputs
    //------------------------------------------------
    assign regA = A;
    assign regB = B;
    assign regC = C;
    assign regD = D;
endmodule

Week 5/tb_register_file.v
`timescale 1ns / 1ps

module tb_register_file;

    // Inputs
    reg clk;
    reg reset;
    reg reg_write;

    reg [1:0] write_sel;
    reg [1:0] read_sel1;
    reg [1:0] read_sel2;

    reg [7:0] write_data;

    // Outputs
    wire [7:0] read_data1;
    wire [7:0] read_data2;

    wire [7:0] regA;
    wire [7:0] regB;
    wire [7:0] regC;
    wire [7:0] regD;

    //--------------------------------------------------
    // Instantiate Register File
    //--------------------------------------------------

    register_file uut (

        .clk(clk),
        .reset(reset),

        .reg_write(reg_write),

        .write_sel(write_sel),
        .read_sel1(read_sel1),
        .read_sel2(read_sel2),

        .write_data(write_data),

        .read_data1(read_data1),
        .read_data2(read_data2),

        .regA(regA),
        .regB(regB),
        .regC(regC),
        .regD(regD)

    );

    //--------------------------------------------------
    // Clock Generation
    //--------------------------------------------------

    always #5 clk = ~clk;

    //--------------------------------------------------
    // Test Sequence
    //--------------------------------------------------

    initial begin

        // Generate waveform
        $dumpfile("register_file.vcd");
        $dumpvars(0, tb_register_file);
        $monitor(
                    "t=%0t | A=%0d B=%0d C=%0d D=%0d | RD1=%0d RD2=%0d",
                    $time,
                    regA, regB, regC, regD,
                    read_data1, read_data2
                );

        clk = 0;
        reset = 1;
        reg_write = 0;

        write_sel = 2'b00;
        read_sel1 = 2'b00;
        read_sel2 = 2'b00;
        write_data = 8'd0;

        #10;

        //------------------------------------------
        // Release Reset
        //------------------------------------------

        reset = 0;

        //------------------------------------------
        // Write 25 to Register A
        //------------------------------------------

        reg_write = 1;
        write_sel = 2'b00;
        write_data = 8'd25;

        #10;

        //------------------------------------------
        // Write 40 to Register B
        //------------------------------------------

        write_sel = 2'b01;
        write_data = 8'd40;

        #10;

        //------------------------------------------
        // Write 75 to Register C
        //------------------------------------------

        write_sel = 2'b10;
        write_data = 8'd75;

        #10;

        //------------------------------------------
        // Write 100 to Register D
        //------------------------------------------

        write_sel = 2'b11;
        write_data = 8'd100;

        #10;

        reg_write = 0;

        //------------------------------------------
        // Read A and B
        //------------------------------------------

        read_sel1 = 2'b00;
        read_sel2 = 2'b01;

        #10;

        //------------------------------------------
        // Read C and D
        //------------------------------------------

        read_sel1 = 2'b10;
        read_sel2 = 2'b11;

        #10;

        //------------------------------------------
        // Read B and D
        //------------------------------------------

        read_sel1 = 2'b01;
        read_sel2 = 2'b11;

        #10;

        //------------------------------------------
        // Finish
        //------------------------------------------

        $finish;

    end

endmodule

Week 5/register_file.vcd
$date
	Wed Jul 15 16:54:58 2026
$end
$version
	Icarus Verilog
$end
$timescale
	1ps
$end
$scope module tb_register_file $end
$var wire 8 ! regD [7:0] $end
$var wire 8 " regC [7:0] $end
$var wire 8 # regB [7:0] $end
$var wire 8 $ regA [7:0] $end
$var wire 8 % read_data2 [7:0] $end
$var wire 8 & read_data1 [7:0] $end
$var reg 1 ' clk $end
$var reg 2 ( read_sel1 [1:0] $end
$var reg 2 ) read_sel2 [1:0] $end
$var reg 1 * reg_write $end
$var reg 1 + reset $end
$var reg 8 , write_data [7:0] $end
$var reg 2 - write_sel [1:0] $end
$scope module uut $end
$var wire 1 ' clk $end
$var wire 2 . read_sel1 [1:0] $end
$var wire 2 / read_sel2 [1:0] $end
$var wire 8 0 regA [7:0] $end
$var wire 8 1 regB [7:0] $end
$var wire 8 2 regC [7:0] $end
$var wire 8 3 regD [7:0] $end
$var wire 1 * reg_write $end
$var wire 1 + reset $end
$var wire 8 4 write_data [7:0] $end
$var wire 2 5 write_sel [1:0] $end
$var wire 8 6 read_data2 [7:0] $end
$var wire 8 7 read_data1 [7:0] $end
$var reg 8 8 A [7:0] $end
$var reg 8 9 B [7:0] $end
$var reg 8 : C [7:0] $end
$var reg 8 ; D [7:0] $end
$upscope $end
$upscope $end
$enddefinitions $end
$comment Show the parameter values. $end
$dumpall
$end
#0
$dumpvars
b0 ;
b0 :
b0 9
b0 8
b0 7
b0 6
b0 5
b0 4
b0 3
b0 2
b0 1
b0 0
b0 /
b0 .
b0 -
b0 ,
1+
0*
b0 )
b0 (
0'
b0 &
b0 %
b0 $
b0 #
b0 "
b0 !
$end
#5000
1'
#10000
0'
b11001 ,
b11001 4
1*
0+
#15000
b11001 &
b11001 7
b11001 %
b11001 6
b11001 $
b11001 0
b11001 8
1'
#20000
0'
b101000 ,
b101000 4
b1 -
b1 5
#25000
b101000 #
b101000 1
b101000 9
1'
#30000
0'
b1001011 ,
b1001011 4
b10 -
b10 5
#35000
b1001011 "
b1001011 2
b1001011 :
1'
#40000
0'
b1100100 ,
b1100100 4
b11 -
b11 5
#45000
b1100100 !
b1100100 3
b1100100 ;
1'
#50000
b101000 %
b101000 6
0'
b1 )
b1 /
0*
#55000
1'
#60000
b1100100 %
b1100100 6
b1001011 &
b1001011 7
0'
b11 )
b11 /
b10 (
b10 .
#65000
1'
#70000
b101000 &
b101000 7
0'
b1 (
b1 .
